nxpy_xml-1.0.2-py3.8-nspkg.pth
nxpy/xml/__init__.py
nxpy/xml/util.py
nxpy_xml-1.0.2.dist-info/LICENSE.txt
nxpy_xml-1.0.2.dist-info/METADATA
nxpy_xml-1.0.2.dist-info/WHEEL
nxpy_xml-1.0.2.dist-info/namespace_packages.txt
nxpy_xml-1.0.2.dist-info/top_level.txt
nxpy_xml-1.0.2.dist-info/RECORD
